KeePassLibrary/__init__.py
KeePassLibrary/errors.py
KeePassLibrary/base/__init__.py
KeePassLibrary/base/context.py
KeePassLibrary/base/librarycomponent.py
KeePassLibrary/keywords/__init__.py
KeePassLibrary/keywords/keepassdatabase.py
KeePassLibrary/keywords/keepassentries.py
KeePassLibrary/keywords/keepassentry.py
KeePassLibrary/keywords/keepassgroup.py
KeePassLibrary/keywords/keepassgroups.py
KeePassLibrary/utils/__init__.py
KeePassLibrary/utils/timezone.py
robotframework_keepasslibrary-0.10.0.dist-info/LICENSE
robotframework_keepasslibrary-0.10.0.dist-info/METADATA
robotframework_keepasslibrary-0.10.0.dist-info/WHEEL
robotframework_keepasslibrary-0.10.0.dist-info/top_level.txt
robotframework_keepasslibrary-0.10.0.dist-info/RECORD
