Metadata-Version: 2.1
Name: robotframework-keepasslibrary
Version: 0.10.0
Summary: Robot Framework library for working with KeePass Database
Author-email: William Looman <wlooman@gmail.com>
Project-URL: Homepage, https://github.com/loomanw/robotframework-keepasslibrary
Project-URL: Issues, https://github.com/loomanw/robotframework-keepasslibrary/issues
Classifier: Development Status :: 3 - Alpha
Classifier: License :: OSI Approved :: MIT License
Classifier: Operating System :: OS Independent
Classifier: Programming Language :: Python
Classifier: Programming Language :: Python :: 3
Classifier: Programming Language :: Python :: 3.8
Classifier: Programming Language :: Python :: 3.9
Classifier: Programming Language :: Python :: 3.10
Classifier: Programming Language :: Python :: 3.11
Classifier: Programming Language :: Python :: 3.12
Classifier: Programming Language :: Python :: 3.13
Classifier: Programming Language :: Python :: 3 :: Only
Classifier: Topic :: Security :: Cryptography
Classifier: Topic :: Software Development :: Quality Assurance
Classifier: Topic :: Software Development :: Testing
Classifier: Framework :: Robot Framework
Classifier: Framework :: Robot Framework :: Library
Requires-Python: <3.14,>=3.8
License-File: LICENSE
Requires-Dist: pykeepass ==4.1.1.post1
Requires-Dist: robotframework >=5.0.1
Requires-Dist: robotframework-pythonlibcore >=4.4.1
